synthesis/alu8bit_netlist.v
/* Generated by Yosys 0.68+50 (git sha1 bf86dd7fa-dirty, Release, GNU /usr/bin/x86_64-w64-mingw32-g++ 15.2.1) */

module alu8bit(A, B, ALU_Sel, ALU_Out, Zero, Carry);
  input [7:0] A;
  wire [7:0] A;
  input [7:0] B;
  wire [7:0] B;
  input [2:0] ALU_Sel;
  wire [2:0] ALU_Sel;
  output [7:0] ALU_Out;
  wire [7:0] ALU_Out;
  output Zero;
  wire Zero;
  output Carry;
  wire Carry;
  wire _000_;
  wire _001_;
  wire _002_;
  wire _003_;
  wire _004_;
  wire _005_;
  wire _006_;
  wire _007_;
  wire _008_;
  wire _009_;
  wire _010_;
  wire _011_;
  wire _012_;
  wire _013_;
  wire _014_;
  wire _015_;
  wire _016_;
  wire _017_;
  wire _018_;
  wire _019_;
  wire _020_;
  wire _021_;
  wire _022_;
  wire _023_;
  wire _024_;
  wire _025_;
  wire _026_;
  wire _027_;
  wire _028_;
  wire _029_;
  wire _030_;
  wire _031_;
  wire _032_;
  wire _033_;
  wire _034_;
  wire _035_;
  wire _036_;
  wire _037_;
  wire _038_;
  wire _039_;
  wire _040_;
  wire _041_;
  wire _042_;
  wire _043_;
  wire _044_;
  wire _045_;
  wire _046_;
  wire _047_;
  wire _048_;
  wire _049_;
  wire _050_;
  wire _051_;
  wire _052_;
  wire _053_;
  wire _054_;
  wire _055_;
  wire _056_;
  wire _057_;
  wire _058_;
  wire _059_;
  wire _060_;
  wire _061_;
  wire _062_;
  wire _063_;
  wire _064_;
  wire _065_;
  wire _066_;
  wire _067_;
  wire _068_;
  wire _069_;
  wire _070_;
  wire _071_;
  wire _072_;
  wire _073_;
  wire _074_;
  wire _075_;
  wire _076_;
  wire _077_;
  wire _078_;
  wire _079_;
  wire _080_;
  wire _081_;
  wire _082_;
  wire _083_;
  wire _084_;
  wire _085_;
  wire _086_;
  wire _087_;
  wire _088_;
  wire _089_;
  wire _090_;
  wire _091_;
  wire _092_;
  wire _093_;
  wire _094_;
  wire _095_;
  wire _096_;
  wire _097_;
  wire _098_;
  wire _099_;
  wire _100_;
  wire _101_;
  wire _102_;
  wire _103_;
  wire _104_;
  wire _105_;
  wire _106_;
  wire _107_;
  wire _108_;
  wire _109_;
  wire _110_;
  wire _111_;
  wire _112_;
  wire _113_;
  wire _114_;
  wire _115_;
  wire _116_;
  wire _117_;
  wire _118_;
  wire _119_;
  wire _120_;
  wire _121_;
  wire _122_;
  wire _123_;
  wire _124_;
  wire _125_;
  wire _126_;
  wire _127_;
  wire _128_;
  wire _129_;
  wire _130_;
  wire _131_;
  wire _132_;
  wire _133_;
  wire _134_;
  wire _135_;
  wire _136_;
  wire _137_;
  wire _138_;
  wire _139_;
  wire _140_;
  wire _141_;
  wire _142_;
  wire _143_;
  wire _144_;
  wire _145_;
  wire _146_;
  wire _147_;
  wire _148_;
  wire _149_;
  wire _150_;
  wire _151_;
  wire _152_;
  wire _153_;
  wire _154_;
  wire _155_;
  wire _156_;
  wire _157_;
  wire _158_;
  wire _159_;
  wire _160_;
  wire _161_;
  wire _162_;
  wire _163_;
  wire _164_;
  wire _165_;
  wire _166_;
  wire _167_;
  wire _168_;
  wire _169_;
  wire _170_;
  wire _171_;
  wire _172_;
  wire _173_;
  wire _174_;
  wire _175_;
  wire _176_;
  wire _177_;
  wire _178_;
  wire _179_;
  wire _180_;
  wire _181_;
  wire _182_;
  wire _183_;
  wire _184_;
  wire _185_;
  wire _186_;
  wire _187_;
  wire _188_;
  wire _189_;
  wire _190_;
  wire _191_;
  wire _192_;
  wire _193_;
  wire _194_;
  wire _195_;
  wire _196_;
  wire _197_;
  wire _198_;
  wire _199_;
  wire _200_;
  wire _201_;
  wire _202_;
  wire _203_;
  wire _204_;
  wire _205_;
  wire carry_out;
  assign _136_ = B[6] | ~(A[6]);
  assign _137_ = A[6] ^ B[6];
  assign _138_ = B[5] | ~(A[5]);
  assign _139_ = ~(A[5] & B[5]);
  assign _140_ = ~(A[5] | B[5]);
  assign _141_ = _139_ & ~(_140_);
  assign _142_ = B[4] | ~(A[4]);
  assign _143_ = ~(A[4] & B[4]);
  assign _144_ = ~(A[4] | B[4]);
  assign _145_ = _143_ & ~(_144_);
  assign _146_ = B[3] | ~(A[3]);
  assign _147_ = ~(A[3] & B[3]);
  assign _148_ = A[3] | B[3];
  assign _149_ = _147_ & _148_;
  assign _150_ = B[2] | ~(A[2]);
  assign _151_ = ~(A[2] & B[2]);
  assign _152_ = A[2] | B[2];
  assign _153_ = ~(_151_ & _152_);
  assign _154_ = B[1] | ~(A[1]);
  assign _155_ = ~(A[1] & B[1]);
  assign _156_ = ~(A[1] | B[1]);
  assign _157_ = ~(A[1] ^ B[1]);
  assign _158_ = A[0] & B[0];
  assign _159_ = ~(A[0] | B[0]);
  assign _160_ = ~(_158_ | _159_);
  assign _161_ = A[0] | ~(B[0]);
  assign _162_ = ~(_157_ & _161_);
  assign _163_ = ~(_154_ & _162_);
  assign _164_ = ~(_153_ & _163_);
  assign _165_ = _150_ & _164_;
  assign _166_ = _149_ | _165_;
  assign _167_ = _146_ & _166_;
  assign _168_ = _145_ | _167_;
  assign _169_ = _142_ & _168_;
  assign _170_ = _141_ | _169_;
  assign _171_ = ~(_138_ & _170_);
  assign _172_ = ALU_Sel[0] & ~(ALU_Sel[1]);
  assign _173_ = _172_ & ~(ALU_Sel[2]);
  assign _174_ = _137_ | ~(_171_);
  assign _175_ = ~(_137_ ^ _171_);
  assign _176_ = ~(_173_ & _175_);
  assign _177_ = _155_ & ~(_158_);
  assign _178_ = _156_ | _177_;
  assign _179_ = _153_ | _178_;
  assign _180_ = ~(_151_ & _179_);
  assign _181_ = ~(_148_ & _180_);
  assign _182_ = ~(_147_ & _181_);
  assign _183_ = ~(_145_ & _182_);
  assign _184_ = ~(_143_ & _183_);
  assign _185_ = ~(_141_ & _184_);
  assign _186_ = ~(_139_ & _185_);
  assign _187_ = ~(ALU_Sel[0] | ALU_Sel[1]);
  assign _188_ = _187_ & ~(ALU_Sel[2]);
  assign _189_ = ~(_137_ & _186_);
  assign _190_ = _137_ ^ _186_;
  assign _191_ = ~(_188_ & _190_);
  assign _192_ = A[6] | B[6];
  assign _193_ = ALU_Sel[0] & ALU_Sel[1];
  assign _194_ = ALU_Sel[2] | ~(_193_);
  assign _195_ = ALU_Sel[2] & _187_;
  assign _196_ = ~(A[6] & B[6]);
  assign _197_ = ~(_195_ & _196_);
  assign _198_ = ~(_194_ & _197_);
  assign _199_ = ~(_192_ & _198_);
  assign _200_ = ALU_Sel[1] & ~(ALU_Sel[0]);
  assign _201_ = ALU_Sel[2] & _200_;
  assign _202_ = ~(A[5] & _201_);
  assign _203_ = ALU_Sel[2] & _193_;
  assign _204_ = ~(A[7] & _203_);
  assign _205_ = _202_ & _204_;
  assign _000_ = ~(ALU_Sel[2] & _172_);
  assign _001_ = A[6] | _000_;
  assign _002_ = _200_ & ~(ALU_Sel[2]);
  assign _003_ = _196_ | ~(_002_);
  assign _004_ = _001_ & _003_;
  assign _005_ = _205_ & _004_;
  assign _006_ = _199_ & _005_;
  assign _007_ = _191_ & _006_;
  assign ALU_Out[6] = ~(_176_ & _007_);
  assign _008_ = ~(_141_ & _169_);
  assign _009_ = _170_ & _173_;
  assign _010_ = ~(_008_ & _009_);
  assign _011_ = _141_ ^ _184_;
  assign _012_ = ~(_188_ & _011_);
  assign _013_ = _140_ | _194_;
  assign _014_ = ~(_141_ & _195_);
  assign _015_ = _013_ & _014_;
  assign _016_ = ~(A[4] & _201_);
  assign _017_ = ~(A[6] & _203_);
  assign _018_ = _016_ & _017_;
  assign _019_ = _139_ | ~(_002_);
  assign _020_ = A[5] | _000_;
  assign _021_ = _019_ & _020_;
  assign _022_ = _018_ & _021_;
  assign _023_ = _015_ & _022_;
  assign _024_ = _012_ & _023_;
  assign ALU_Out[5] = ~(_010_ & _024_);
  assign _025_ = ~(_145_ & _167_);
  assign _026_ = _168_ & _173_;
  assign _027_ = ~(_025_ & _026_);
  assign _028_ = _145_ ^ _182_;
  assign _029_ = ~(_188_ & _028_);
  assign _030_ = _144_ | _194_;
  assign _031_ = ~(_145_ & _195_);
  assign _032_ = _030_ & _031_;
  assign _033_ = A[4] | _000_;
  assign _034_ = ~(A[5] & _203_);
  assign _035_ = _033_ & _034_;
  assign _036_ = ~(A[3] & _201_);
  assign _037_ = _143_ | ~(_002_);
  assign _038_ = _036_ & _037_;
  assign _039_ = _035_ & _038_;
  assign _040_ = _032_ & _039_;
  assign _041_ = _029_ & _040_;
  assign ALU_Out[4] = ~(_027_ & _041_);
  assign _042_ = ~(_149_ & _165_);
  assign _043_ = _166_ & _173_;
  assign _044_ = ~(_042_ & _043_);
  assign _045_ = _149_ ^ _180_;
  assign _046_ = ~(_188_ & _045_);
  assign _047_ = _147_ | ~(_002_);
  assign _048_ = ~(_149_ & _195_);
  assign _049_ = _194_ | ~(_148_);
  assign _050_ = ~(A[2] & _201_);
  assign _051_ = ~(A[4] & _203_);
  assign _052_ = A[3] | _000_;
  assign _053_ = _048_ & _049_;
  assign _054_ = _050_ & _053_;
  assign _055_ = _047_ & _051_;
  assign _056_ = _052_ & _055_;
  assign _057_ = _054_ & _056_;
  assign _058_ = _046_ & _057_;
  assign ALU_Out[3] = ~(_044_ & _058_);
  assign _059_ = _153_ ^ _163_;
  assign _060_ = ~(_173_ & _059_);
  assign _061_ = ~(_153_ & _178_);
  assign _062_ = _188_ & _061_;
  assign _063_ = ~(_179_ & _062_);
  assign _064_ = ~(_151_ & _195_);
  assign _065_ = ~(_194_ & _064_);
  assign _066_ = ~(_152_ & _065_);
  assign _067_ = _151_ | ~(_002_);
  assign _068_ = A[2] | _000_;
  assign _069_ = _067_ & _068_;
  assign _070_ = ~(A[3] & _203_);
  assign _071_ = ~(A[1] & _201_);
  assign _072_ = _070_ & _071_;
  assign _073_ = _069_ & _072_;
  assign _074_ = _066_ & _073_;
  assign _075_ = _063_ & _074_;
  assign ALU_Out[2] = ~(_060_ & _075_);
  assign _076_ = _157_ ^ _161_;
  assign _077_ = ~(_173_ & _076_);
  assign _078_ = _158_ & ~(ALU_Sel[2]);
  assign _079_ = ~(_157_ ^ _078_);
  assign _080_ = ~(_187_ & _079_);
  assign _081_ = ~(A[0] & _201_);
  assign _082_ = _155_ | ~(_002_);
  assign _083_ = _156_ | _194_;
  assign _084_ = ~(A[2] & _203_);
  assign _085_ = A[1] | _000_;
  assign _086_ = _083_ & _084_;
  assign _087_ = _080_ & _086_;
  assign _088_ = _082_ & _085_;
  assign _089_ = _081_ & _088_;
  assign _090_ = _077_ & _089_;
  assign ALU_Out[1] = ~(_087_ & _090_);
  assign _091_ = _173_ | _187_;
  assign _092_ = ~(_160_ & _091_);
  assign _093_ = _159_ | _194_;
  assign _094_ = ~(_158_ & _002_);
  assign _095_ = _093_ & _094_;
  assign _096_ = A[0] | _000_;
  assign _097_ = ~(A[1] & _203_);
  assign _098_ = _096_ & _097_;
  assign _099_ = _095_ & _098_;
  assign ALU_Out[0] = ~(_092_ & _099_);
  assign _100_ = B[7] & ~(A[7]);
  assign _101_ = B[7] | ~(A[7]);
  assign _102_ = ~(A[7] ^ B[7]);
  assign _103_ = _136_ & _174_;
  assign _104_ = ~(_102_ ^ _103_);
  assign _105_ = ~(_173_ & _104_);
  assign _106_ = _189_ & _196_;
  assign _107_ = ~(_102_ & _106_);
  assign _108_ = _102_ | _106_;
  assign _109_ = _188_ & _108_;
  assign _110_ = ~(_107_ & _109_);
  assign _111_ = A[7] | B[7];
  assign _112_ = ~(A[7] & B[7]);
  assign _113_ = ~(_195_ & _112_);
  assign _114_ = ~(_194_ & _113_);
  assign _115_ = ~(_111_ & _114_);
  assign _116_ = A[7] | _000_;
  assign _117_ = ~(A[6] & _201_);
  assign _118_ = _002_ & ~(_112_);
  assign _119_ = _117_ & ~(_118_);
  assign _120_ = _116_ & _119_;
  assign _121_ = _115_ & _120_;
  assign _122_ = _110_ & _121_;
  assign ALU_Out[7] = ~(_105_ & _122_);
  assign _123_ = ~(_108_ & _112_);
  assign _124_ = ~(_188_ & _123_);
  assign _125_ = _174_ | ~(_102_);
  assign _126_ = _136_ | _100_;
  assign _127_ = _173_ & _101_;
  assign _128_ = _126_ & _127_;
  assign _129_ = ~(_125_ & _128_);
  assign Carry = ~(_124_ & _129_);
  assign _130_ = ALU_Out[1] | ALU_Out[0];
  assign _131_ = ALU_Out[2] | _130_;
  assign _132_ = ALU_Out[3] | _131_;
  assign _133_ = ALU_Out[4] | _132_;
  assign _134_ = ALU_Out[5] | _133_;
  assign _135_ = ALU_Out[6] | _134_;
  assign Zero = ~(ALU_Out[7] | _135_);
  assign carry_out = Carry;
endmodule

Task2/tb/alu8bit_gate_tb.v
//testbench:
module alu8bit_tb;

reg [7:0] A;
reg [7:0] B;
reg [2:0] ALU_Sel;
wire [7:0] ALU_Out;
wire Zero;
wire Carry;
alu8bit a8b (A,B,ALU_Sel,ALU_Out,Zero,Carry);
initial begin
  $dumpfile("gate.vcd");
  $dumpvars(0, alu8bit_tb);
    A=8'd10;
    B=8'd5;
    ALU_Sel=3'b000;#5
    ALU_Sel=3'b001;#5
    ALU_Sel=3'b010;#5
    ALU_Sel=3'b011;#5
    ALU_Sel=3'b100;#5
    ALU_Sel=3'b101;#5
   ALU_Sel=3'b110;#5
   ALU_Sel=3'b111;#5
    $finish;
end
endmodule

Task2/simulation/gate.vcd
$date
	Thu Aug 13 14:20:18 2026
$end
$version
	Icarus Verilog
$end
$timescale
	1s
$end
$scope module alu8bit_tb $end
$var wire 1 ! Zero $end
$var wire 1 " Carry $end
$var wire 8 # ALU_Out [7:0] $end
$var reg 8 $ A [7:0] $end
$var reg 3 % ALU_Sel [2:0] $end
$var reg 8 & B [7:0] $end
$scope module a8b $end
$var wire 8 ' A [7:0] $end
$var wire 3 ( ALU_Sel [2:0] $end
$var wire 8 ) B [7:0] $end
$var wire 1 " Carry $end
$var wire 1 ! Zero $end
$var wire 1 * _000_ $end
$var wire 1 + _001_ $end
$var wire 1 , _002_ $end
$var wire 1 - _003_ $end
$var wire 1 . _004_ $end
$var wire 1 / _005_ $end
$var wire 1 0 _006_ $end
$var wire 1 1 _007_ $end
$var wire 1 2 _008_ $end
$var wire 1 3 _009_ $end
$var wire 1 4 _010_ $end
$var wire 1 5 _011_ $end
$var wire 1 6 _012_ $end
$var wire 1 7 _013_ $end
$var wire 1 8 _014_ $end
$var wire 1 9 _015_ $end
$var wire 1 : _016_ $end
$var wire 1 ; _017_ $end
$var wire 1 < _018_ $end
$var wire 1 = _019_ $end
$var wire 1 > _020_ $end
$var wire 1 ? _021_ $end
$var wire 1 @ _022_ $end
$var wire 1 A _023_ $end
$var wire 1 B _024_ $end
$var wire 1 C _025_ $end
$var wire 1 D _026_ $end
$var wire 1 E _027_ $end
$var wire 1 F _028_ $end
$var wire 1 G _029_ $end
$var wire 1 H _030_ $end
$var wire 1 I _031_ $end
$var wire 1 J _032_ $end
$var wire 1 K _033_ $end
$var wire 1 L _034_ $end
$var wire 1 M _035_ $end
$var wire 1 N _036_ $end
$var wire 1 O _037_ $end
$var wire 1 P _038_ $end
$var wire 1 Q _039_ $end
$var wire 1 R _040_ $end
$var wire 1 S _041_ $end
$var wire 1 T _042_ $end
$var wire 1 U _043_ $end
$var wire 1 V _044_ $end
$var wire 1 W _045_ $end
$var wire 1 X _046_ $end
$var wire 1 Y _047_ $end
$var wire 1 Z _048_ $end
$var wire 1 [ _049_ $end
$var wire 1 \ _050_ $end
$var wire 1 ] _051_ $end
$var wire 1 ^ _052_ $end
$var wire 1 _ _053_ $end
$var wire 1 ` _054_ $end
$var wire 1 a _055_ $end
$var wire 1 b _056_ $end
$var wire 1 c _057_ $end
$var wire 1 d _058_ $end
$var wire 1 e _059_ $end
$var wire 1 f _060_ $end
$var wire 1 g _061_ $end
$var wire 1 h _062_ $end
$var wire 1 i _063_ $end
$var wire 1 j _064_ $end
$var wire 1 k _065_ $end
$var wire 1 l _066_ $end
$var wire 1 m _067_ $end
$var wire 1 n _068_ $end
$var wire 1 o _069_ $end
$var wire 1 p _070_ $end
$var wire 1 q _071_ $end
$var wire 1 r _072_ $end
$var wire 1 s _073_ $end
$var wire 1 t _074_ $end
$var wire 1 u _075_ $end
$var wire 1 v _076_ $end
$var wire 1 w _077_ $end
$var wire 1 x _078_ $end
$var wire 1 y _079_ $end
$var wire 1 z _080_ $end
$var wire 1 { _081_ $end
$var wire 1 | _082_ $end
$var wire 1 } _083_ $end
$var wire 1 ~ _084_ $end
$var wire 1 !" _085_ $end
$var wire 1 "" _086_ $end
$var wire 1 #" _087_ $end
$var wire 1 $" _088_ $end
$var wire 1 %" _089_ $end
$var wire 1 &" _090_ $end
$var wire 1 '" _091_ $end
$var wire 1 (" _092_ $end
$var wire 1 )" _093_ $end
$var wire 1 *" _094_ $end
$var wire 1 +" _095_ $end
$var wire 1 ," _096_ $end
$var wire 1 -" _097_ $end
$var wire 1 ." _098_ $end
$var wire 1 /" _099_ $end
$var wire 1 0" _100_ $end
$var wire 1 1" _101_ $end
$var wire 1 2" _102_ $end
$var wire 1 3" _103_ $end
$var wire 1 4" _104_ $end
$var wire 1 5" _105_ $end
$var wire 1 6" _106_ $end
$var wire 1 7" _107_ $end
$var wire 1 8" _108_ $end
$var wire 1 9" _109_ $end
$var wire 1 :" _110_ $end
$var wire 1 ;" _111_ $end
$var wire 1 <" _112_ $end
$var wire 1 =" _113_ $end
$var wire 1 >" _114_ $end
$var wire 1 ?" _115_ $end
$var wire 1 @" _116_ $end
$var wire 1 A" _117_ $end
$var wire 1 B" _118_ $end
$var wire 1 C" _119_ $end
$var wire 1 D" _120_ $end
$var wire 1 E" _121_ $end
$var wire 1 F" _122_ $end
$var wire 1 G" _123_ $end
$var wire 1 H" _124_ $end
$var wire 1 I" _125_ $end
$var wire 1 J" _126_ $end
$var wire 1 K" _127_ $end
$var wire 1 L" _128_ $end
$var wire 1 M" _129_ $end
$var wire 1 N" _130_ $end
$var wire 1 O" _131_ $end
$var wire 1 P" _132_ $end
$var wire 1 Q" _133_ $end
$var wire 1 R" _134_ $end
$var wire 1 S" _135_ $end
$var wire 1 T" _136_ $end
$var wire 1 U" _137_ $end
$var wire 1 V" _138_ $end
$var wire 1 W" _139_ $end
$var wire 1 X" _140_ $end
$var wire 1 Y" _141_ $end
$var wire 1 Z" _142_ $end
$var wire 1 [" _143_ $end
$var wire 1 \" _144_ $end
$var wire 1 ]" _145_ $end
$var wire 1 ^" _146_ $end
$var wire 1 _" _147_ $end
$var wire 1 `" _148_ $end
$var wire 1 a" _149_ $end
$var wire 1 b" _150_ $end
$var wire 1 c" _151_ $end
$var wire 1 d" _152_ $end
$var wire 1 e" _153_ $end
$var wire 1 f" _154_ $end
$var wire 1 g" _155_ $end
$var wire 1 h" _156_ $end
$var wire 1 i" _157_ $end
$var wire 1 j" _158_ $end
$var wire 1 k" _159_ $end
$var wire 1 l" _160_ $end
$var wire 1 m" _161_ $end
$var wire 1 n" _162_ $end
$var wire 1 o" _163_ $end
$var wire 1 p" _164_ $end
$var wire 1 q" _165_ $end
$var wire 1 r" _166_ $end
$var wire 1 s" _167_ $end
$var wire 1 t" _168_ $end
$var wire 1 u" _169_ $end
$var wire 1 v" _170_ $end
$var wire 1 w" _171_ $end
$var wire 1 x" _172_ $end
$var wire 1 y" _173_ $end
$var wire 1 z" _174_ $end
$var wire 1 {" _175_ $end
$var wire 1 |" _176_ $end
$var wire 1 }" _177_ $end
$var wire 1 ~" _178_ $end
$var wire 1 !# _179_ $end
$var wire 1 "# _180_ $end
$var wire 1 ## _181_ $end
$var wire 1 $# _182_ $end
$var wire 1 %# _183_ $end
$var wire 1 &# _184_ $end
$var wire 1 '# _185_ $end
$var wire 1 (# _186_ $end
$var wire 1 )# _187_ $end
$var wire 1 *# _188_ $end
$var wire 1 +# _189_ $end
$var wire 1 ,# _190_ $end
$var wire 1 -# _191_ $end
$var wire 1 .# _192_ $end
$var wire 1 /# _193_ $end
$var wire 1 0# _194_ $end
$var wire 1 1# _195_ $end
$var wire 1 2# _196_ $end
$var wire 1 3# _197_ $end
$var wire 1 4# _198_ $end
$var wire 1 5# _199_ $end
$var wire 1 6# _200_ $end
$var wire 1 7# _201_ $end
$var wire 1 8# _202_ $end
$var wire 1 9# _203_ $end
$var wire 1 :# _204_ $end
$var wire 1 ;# _205_ $end
$var wire 1 <# carry_out $end
$var wire 8 =# ALU_Out [7:0] $end
$upscope $end
$upscope $end
$enddefinitions $end
$comment Show the parameter values. $end
$dumpall
$end
#0
$dumpvars
b1111 =#
0<#
1;#
1:#
09#
18#
07#
06#
15#
04#
13#
12#
01#
10#
0/#
0.#
1-#
0,#
1+#
1*#
1)#
0(#
1'#
0&#
1%#
0$#
1##
0"#
1!#
1~"
1}"
1|"
0{"
0z"
0y"
0x"
1w"
0v"
0u"
0t"
0s"
1r"
1q"
1p"
1o"
1n"
0m"
1l"
0k"
0j"
0i"
0h"
1g"
0f"
0e"
1d"
1c"
1b"
1a"
1`"
1_"
0^"
0]"
1\"
1["
1Z"
0Y"
1X"
1W"
1V"
0U"
1T"
1S"
1R"
1Q"
1P"
1O"
1N"
1M"
0L"
0K"
1J"
0I"
1H"
0G"
1F"
1E"
1D"
1C"
0B"
1A"
1@"
1?"
0>"
1="
1<"
0;"
1:"
19"
18"
07"
16"
15"
04"
03"
12"
11"
00"
1/"
1."
1-"
1,"
1+"
1*"
1)"
0("
1'"
1&"
1%"
1$"
0#"
1""
1!"
1~
1}
1|
1{
0z
1y
0x
1w
0v
0u
1t
1s
1r
1q
1p
1o
1n
1m
1l
0k
1j
0i
1h
1g
1f
1e
0d
1c
1b
1a
1`
1_
1^
1]
1\
1[
1Z
1Y
0X
1W
1V
0U
0T
1S
1R
1Q
1P
1O
1N
1M
1L
1K
1J
1I
1H
1G
0F
1E
0D
1C
1B
1A
1@
1?
1>
1=
1<
1;
1:
19
18
17
16
05
14
03
12
11
10
1/
1.
1-
0,
1+
1*
b101 )
b0 (
b1010 '
b101 &
b0 %
b1010 $
b1111 #
0"
0!
$end
#5
b101 #
b101 =#
1u
1d
1i
1X
1#"
0f
1L"
0h
09"
1z
1U
1K"
0*#
1y"
0)#
1x"
b1 %
b1 (
#10
1!
0S"
0R"
0Q"
0P"
0O"
0N"
b0 #
b0 =#
1("
1f
0L"
0U
0'"
0K"
0y"
1,
0x"
16#
b10 %
b10 (
#15
0!
1S"
1R"
1Q"
1P"
1O"
1N"
b1111 #
b1111 =#
0u
0d
0t
0c
0l
0`
0#"
0/"
14#
0_
1k
0""
0+"
1>"
0[
0}
0)"
00#
0,
06#
1/#
b11 %
b11 (
#20
0u
b1111 #
b1111 =#
0t
1/"
0d
03#
0Z
0j
0="
0("
0c
0l
1s
0z
0`
0#"
1r
1."
11#
1'"
14#
0_
1k
1""
1+"
1>"
1p
1-"
1)#
1[
1}
1)"
0/#
10#
09#
b100 %
b100 (
#25
1N"
1d
1l
b11110101 #
b11110101 =#
01
0B
0S
1c
00
0A
0R
0F"
04#
1`
0k
0>"
0/
0@
0Q
0s
0/"
0E"
1_
0.
0?
0M
0o
0."
0D"
13#
1Z
1j
1="
1#"
1("
0+
0>
0K
0n
0,"
0@"
1z
0*
01#
0'"
0)#
1x"
b101 %
b101 (
#30
0N"
b10100 #
b10100 =#
11
1B
10
1A
1F"
1/
1@
1/"
1E"
1.
1?
1M
1o
1."
1D"
0P
0r
1+
1>
1K
1n
1,"
1@"
0N
0q
1*
17#
0x"
16#
b110 %
b110 (
#35
1N"
b101 #
b101 =#
1S
1R
1Q
0/"
1P
0."
1N
1q
0p
0-"
07#
19#
06#
1/#
b111 %
b111 (
