rtl/alu8bit.v
module alu8bit (
    input  [7:0] A,
    input  [7:0] B,
    input  [2:0] ALU_Sel,
    output reg [7:0] ALU_Out,
    output Zero,
    output Carry
);

reg carry_out;

always @(*) begin
    carry_out = 1'b0;

    case (ALU_Sel)
        3'b000: begin
            {carry_out, ALU_Out} = A + B;      // Addition
        end

        3'b001: begin
            {carry_out, ALU_Out} = A - B;      // Subtraction
        end

        3'b010: begin
            ALU_Out = A & B;                   // AND
        end

        3'b011: begin
            ALU_Out = A | B;                   // OR
        end

        3'b100: begin
            ALU_Out = A ^ B;                   // XOR
        end

        3'b101: begin
            ALU_Out = ~A;                      // NOT
        end

        3'b110: begin
            ALU_Out = A << 1;                  // Left Shift
        end

        3'b111: begin
            ALU_Out = A >> 1;                  // Right Shift
        end

        default: begin
            ALU_Out = 8'b00000000;
        end
    endcase
end

assign Zero  = (ALU_Out == 8'b00000000);
assign Carry = carry_out;

endmodule

tb/alu8bit_tb.v
//testbench:
module alu8bit_tb;

reg [7:0] A;
reg [7:0] B;
reg [2:0] ALU_Sel;
wire [7:0] ALU_Out;
wire Zero;
wire Carry;
alu8bit a8b (A,B,ALU_Sel,ALU_Out,Zero,Carry);
initial begin
  $dumpfile("wave.vcd");
  $dumpvars(0, alu8bit_tb);
    A=8'd10;
    B=8'd5;
    ALU_Sel=3'b000;#5
    ALU_Sel=3'b001;#5
    ALU_Sel=3'b010;#5
    ALU_Sel=3'b011;#5
    ALU_Sel=3'b100;#5
    ALU_Sel=3'b101;#5
   ALU_Sel=3'b110;#5
   ALU_Sel=3'b111;#5
    $finish;
end
endmodule

simulation/wave.vcd
$date
	Thu Aug 13 12:45:00 2026
$end
$version
	Icarus Verilog
$end
$timescale
	1s
$end
$scope module alu8bit_tb $end
$var wire 1 ! Zero $end
$var wire 1 " Carry $end
$var wire 8 # ALU_Out [7:0] $end
$var reg 8 $ A [7:0] $end
$var reg 3 % ALU_Sel [2:0] $end
$var reg 8 & B [7:0] $end
$scope module a8b $end
$var wire 8 ' A [7:0] $end
$var wire 3 ( ALU_Sel [2:0] $end
$var wire 8 ) B [7:0] $end
$var wire 1 " Carry $end
$var wire 1 ! Zero $end
$var reg 8 * ALU_Out [7:0] $end
$var reg 1 + carry_out $end
$upscope $end
$upscope $end
$enddefinitions $end
$comment Show the parameter values. $end
$dumpall
$end
#0
$dumpvars
0+
b1111 *
b101 )
b0 (
b1010 '
b101 &
b0 %
b1010 $
b1111 #
0"
0!
$end
#5
b101 #
b101 *
b1 %
b1 (
#10
1!
b0 #
b0 *
b10 %
b10 (
#15
0!
b1111 #
b1111 *
b11 %
b11 (
#20
b100 %
b100 (
#25
b11110101 #
b11110101 *
b101 %
b101 (
#30
b10100 #
b10100 *
b110 %
b110 (
#35
b101 #
b101 *
b111 %
b111 (
